aiida_gui/__init__.py
aiida_gui/cmd_web.py
aiida_gui/main.py
aiida_gui/app/__init__.py
aiida_gui/app/api.py
aiida_gui/app/daemon.py
aiida_gui/app/data_node.py
aiida_gui/app/group_node.py
aiida_gui/app/node_table.py
aiida_gui/app/plugin.py
aiida_gui/app/process_node.py
aiida_gui/app/task.py
aiida_gui/app/utils.py
aiida_gui/app/workchain.py
aiida_gui/static/asset-manifest.json
aiida_gui/static/favicon.ico
aiida_gui/static/index.html
aiida_gui/static/manifest.json
aiida_gui/static/react-jsx-runtime-shim.js
aiida_gui/static/react-router-dom-shim.js
aiida_gui/static/react-shim.js
aiida_gui/static/robots.txt
aiida_gui/static/use-sync-external-store-shim.js
aiida_gui/static/static/css/main.bcd12876.css
aiida_gui/static/static/css/main.bcd12876.css.map
aiida_gui/static/static/js/main.ccc3f06c.js
aiida_gui/static/static/js/main.ccc3f06c.js.LICENSE.txt
aiida_gui/static/static/js/main.ccc3f06c.js.map
aiida_gui-0.2.4.dist-info/entry_points.txt
aiida_gui-0.2.4.dist-info/licenses/LICENSE
aiida_gui-0.2.4.dist-info/WHEEL
aiida_gui-0.2.4.dist-info/METADATA
aiida_gui-0.2.4.dist-info/RECORD
